MANIFEST.in
README.markdown
setup.py
si_news.py
si_news.egg-info/PKG-INFO
si_news.egg-info/SOURCES.txt
si_news.egg-info/dependency_links.txt
si_news.egg-info/entry_points.txt
si_news.egg-info/requires.txt
si_news.egg-info/top_level.txt