Metadata-Version: 1.0
Name: si-news
Version: 0.1.1
Summary: Tracks updates for zhurnal.lib.ru authors
Home-page: https://bitbucket.org/dmalinovsky/si-news/
Author: Denis Malinovsky
Author-email: dmalinovsky@gmail.com
License: gpl
Platform: UNKNOWN
Classifier: Development Status :: 3 - Alpha
Classifier: Environment :: MacOS X
Classifier: Environment :: Win32 (MS Windows)
Classifier: Environment :: X11 Applications :: Qt
Classifier: Intended Audience :: End Users/Desktop
Classifier: License :: OSI Approved :: GNU General Public License (GPL)
Classifier: Natural Language :: Russian
Classifier: Operating System :: OS Independent
Classifier: Programming Language :: Python
Classifier: Topic :: Internet :: WWW/HTTP
Classifier: Topic :: Utilities
